BlackprintRC/Node.py
BlackprintRC/PuppetNode.py
BlackprintRC/RemoteBase.py
BlackprintRC/RemoteEngine.py
BlackprintRC/__init__.py
BlackprintRC/utils.py
blackprint_rc-0.2.0.dist-info/licenses/LICENSE
blackprint_rc-0.2.0.dist-info/METADATA
blackprint_rc-0.2.0.dist-info/WHEEL
blackprint_rc-0.2.0.dist-info/top_level.txt
blackprint_rc-0.2.0.dist-info/RECORD
