Metadata-Version: 2.4
Name: blackprint-rc
Version: 0.2.0
Summary: Blackprint Engine remote control feature for Python
Home-page: https://github.com/Blackprint/remote-control
Project-URL: Homepage, https://github.com/Blackprint/remote-control
Project-URL: Bug Tracker, https://github.com/Blackprint/remote-control/issues
Classifier: Programming Language :: Python :: 3
Classifier: License :: OSI Approved :: MIT License
Classifier: Development Status :: 4 - Beta
Requires-Python: >=3.10
License-File: LICENSE
Dynamic: home-page
Dynamic: license-file
